{
  "meta": {
    "slug": "5-series-518i",
    "title": "518 / 518i Engine Cost UK — Compare Quotes",
    "titleCharCount": 58,
    "description": "BMW 518 and 518i – M10, M40 and M43 engines. Real UK costs, timing belt and timing chain facts, and specialist quotes. Get free prices from 20+ vetted specialists today.",
    "descriptionCharCount": 158,
    "canonical": "https://bmwengine.uk/5-series/518i/",
    "openGraph": {
      "title": "518 / 518i Engine Cost UK — Compare Quotes",
      "description": "BMW 518 and 518i – M10, M40 and M43 engines. Real UK costs, timing belt and timing chain facts, and specialist quotes. Get free prices from 20+ vetted specialists today.",
      "type": "website",
      "url": "https://bmwengine.uk/5-series/518i/",
      "image": "https://bmwengine.uk/images/bmw/hero/518i.jpg",
      "siteName": "BMWEngines.uk"
    },
    "twitter": {
      "card": "summary_large_image",
      "title": "518 / 518i Engine Cost UK — Compare Quotes",
      "description": "BMW 518 and 518i – M10, M40 and M43 engines. Real UK costs, timing belt and timing chain facts, and specialist quotes.",
      "image": "https://bmwengine.uk/images/bmw/hero/518i.jpg"
    },
    "jsonLd": {
      "@context": "https://schema.org",
      "@graph": [
        {
          "@type": "BreadcrumbList",
          "itemListElement": [
            {
              "@type": "ListItem",
              "position": 1,
              "name": "Home",
              "item": "https://bmwengine.uk/"
            },
            {
              "@type": "ListItem",
              "position": 2,
              "name": "5 Series",
              "item": "https://bmwengine.uk/5-series/"
            },
            {
              "@type": "ListItem",
              "position": 3,
              "name": "518 / 518i",
              "item": "https://bmwengine.uk/5-series/518i/"
            }
          ]
        },
        {
          "@type": "ItemList",
          "name": "BMW 518 / 518i Engine Era Map",
          "itemListElement": [
            {
              "@type": "ListItem",
              "position": 1,
              "name": "E12 518 (M10B18 carb, 1974-1981)",
              "url": "https://bmwengine.uk/5-series/e12/"
            },
            {
              "@type": "ListItem",
              "position": 2,
              "name": "E28 518i (M10B18 injection, 1981-1987)",
              "url": "https://bmwengine.uk/5-series/e28/"
            },
            {
              "@type": "ListItem",
              "position": 3,
              "name": "E34 518i (M40B18, 1989-1994)",
              "url": "https://bmwengine.uk/5-series/e34/"
            },
            {
              "@type": "ListItem",
              "position": 4,
              "name": "E34 518i (M43B18, 1994-1995)",
              "url": "https://bmwengine.uk/5-series/e34/"
            },
            {
              "@type": "ListItem",
              "position": 5,
              "name": "E39 518i (M43B19, 1996-2001)",
              "url": "https://bmwengine.uk/5-series/e39/"
            }
          ]
        },
        {
          "@type": "ItemList",
          "name": "BMW 518 / 518i Engine Codes",
          "itemListElement": [
            {
              "@type": "ListItem",
              "position": 1,
              "name": "M10B18 (carb)",
              "url": "https://bmwengine.uk/engines/m10/"
            },
            {
              "@type": "ListItem",
              "position": 2,
              "name": "M10B18 (injection)",
              "url": "https://bmwengine.uk/engines/m10/"
            },
            {
              "@type": "ListItem",
              "position": 3,
              "name": "M40B18",
              "url": "https://bmwengine.uk/engines/m40/"
            },
            {
              "@type": "ListItem",
              "position": 4,
              "name": "M43B18",
              "url": "https://bmwengine.uk/engines/m43/"
            },
            {
              "@type": "ListItem",
              "position": 5,
              "name": "M43B19",
              "url": "https://bmwengine.uk/engines/m43/"
            }
          ]
        },
        {
          "@type": "FAQPage",
          "mainEntity": [
            {
              "@type": "Question",
              "name": "How much does a BMW 518 or 518i engine replacement cost in the UK?",
              "acceptedAnswer": {
                "@type": "Answer",
                "text": "A reconditioned 518/518i engine typically costs £500–£3,500 supply only depending on which generation, with used units available from £400–£1,200. Fitting adds £700–£1,500. Use our calculator for a figure specific to your car."
              }
            },
            {
              "@type": "Question",
              "name": "Is the BMW 518 / 518i engine reliable?",
              "acceptedAnswer": {
                "@type": "Answer",
                "text": "It depends on which generation. The M10 and M40 engines are robust but require regular timing belt changes — a snapped belt is catastrophic. The M43 engines (1994–2001) are significantly more reliable thanks to the timing chain. The M43B19 in the E39 is the most refined and dependable of the four-cylinder 5 Series."
              }
            },
            {
              "@type": "Question",
              "name": "What are the common problems with the BMW 518 and 518i?",
              "acceptedAnswer": {
                "@type": "Answer",
                "text": "M10: timing belt failure (requires regular replacement). M40: timing belt failure and ticking hydraulic lifters. M43: cooling system leaks and head gasket issues. The M43 is the most reliable of the family."
              }
            },
            {
              "@type": "Question",
              "name": "Is it worth replacing a BMW 518 / 518i engine, or should I scrap the car?",
              "acceptedAnswer": {
                "@type": "Answer",
                "text": "Depends on vehicle value and generation. Against a well-kept E39 518i worth £2,000–£5,000, a £1,500–£2,800 recon is 30–60% — borderline but often worth it on a cherished example. Against a tired E12 518 worth £1,000, a £1,000 recon exceeds 70% — get a scrap valuation first."
              }
            },
            {
              "@type": "Question",
              "name": "How do I find my BMW 518 or 518i engine code?",
              "acceptedAnswer": {
                "@type": "Answer",
                "text": "Listed on the VIN plate and vehicle documentation. E12 518 (1974–1981) uses M10B18 carb; E28 518i (1981–1987) uses M10B18 injection; E34 518i (1989–1994) uses M40B18; E34 518i (1994–1995) uses M43B18; E39 518i (1996–2001) uses M43B19. Tell us your registration date and we'll confirm it for free."
              }
            },
            {
              "@type": "Question",
              "name": "Can I repair the M10 / M40 timing belt, or does it need replacement?",
              "acceptedAnswer": {
                "@type": "Answer",
                "text": "The timing belt must be replaced — it's a wear item. Replacement interval is 40,000–60,000 miles or 4–5 years. If the belt snaps, the engine is typically destroyed. A preventative belt replacement (£300–£600) is far cheaper than a full engine replacement (£500–£1,800+). On M43 engines, the timing chain replaces the belt and is much more reliable."
              }
            }
          ]
        },
        {
          "@type": "Organization",
          "name": "BMWEngines.uk",
          "url": "https://bmwengine.uk/",
          "logo": "https://bmwengine.uk/images/bmwengines-logo.png",
          "parentOrganization": {
            "@type": "Organization",
            "name": "Engine Finders"
          }
        },
        {
          "@type": "Service",
          "serviceType": "BMW 518 / 518i Engine Replacement",
          "provider": {
            "@type": "Organization",
            "name": "BMWEngines.uk"
          },
          "areaServed": "GB",
          "offers": {
            "@type": "AggregateOffer",
            "priceCurrency": "GBP",
            "lowPrice": "400",
            "highPrice": "3500",
            "availability": "https://schema.org/InStock"
          }
        },
        {
          "@type": "Dataset",
          "name": "BMW 518 / 518i UK Engine Enquiry Data 2025",
          "description": "Proprietary UK enquiry volumes and demand trends for BMW 518 and 518i engines across all generations, sourced from BMWEngines.uk's specialist marketplace activity.",
          "creator": {
            "@type": "Organization",
            "name": "BMWEngines.uk"
          },
          "temporalCoverage": "2025",
          "spatialCoverage": "United Kingdom"
        },
        {
          "@type": "WebPage",
          "name": "518 / 518i Engine Cost UK — Compare Quotes",
          "url": "https://bmwengine.uk/5-series/518i/",
          "author": {
            "@type": "Organization",
            "name": "BMWEngines.uk Editorial Team"
          },
          "reviewedBy": {
            "@type": "Organization",
            "name": "BMWEngines.uk Specialist Network"
          },
          "datePublished": "2026-07-11",
          "dateModified": "2026-07-11"
        }
      ]
    }
  },
  "hero": {
    "tagPill": "BMW 5 Series 518 / 518i • 1974–2001 • 4 Engine Families",
    "h1": "BMW 518 / 518i Engine Replacement — Compare Prices & Get Quotes",
    "subHeadline": "The 518 and 518i were the entry-level 5 Series for over 25 years — spanning carburettor M10s, fuel-injected M10s, M40s, and the final M43 engines. These simple four-cylinder engines are robust but demand timing belt attention on earlier cars. Get quotes from UK specialists for reconditioned, rebuilt and used units today.",
    "trustBadges": [
      "🔧 Supply & Fit Available",
      "✅ 12-Month Warranty",
      "🚚 Nationwide Delivery",
      "👥 20+ Specialists"
    ],
    "priceAnchor": "BMW 518 / 518i Engines — from £400 to £3,500 · Common codes: M10B18, M40B18, M43B18, M43B19",
    "registrationInput": {
      "flag": "🇬🇧 GB",
      "placeholder": "Enter your reg — e.g. AB12 CDE",
      "cta": {
        "label": "See BMW 518 / 518i Engine Options →",
        "href": "#"
      }
    },
    "ticker": "● Instant Quotes · No Obligation · 100% Free · Reconditioned · Rebuilt · Used · Supply & Fit Available · UK-Wide Network"
  },
  "eraMap": {
    "title": "The 518 / 518i THROUGH TIME — Era Map",
    "columns": [
      "Generation",
      "Years",
      "Engine Code",
      "Reliability",
      "Recon Cost",
      "Era Note"
    ],
    "rows": [],
    "sourceNote": "",
    "dataNote": ""
  },
  "replacementCosts": {
    "h2": "BMW 518 / 518i Engine Replacement Costs",
    "columns": [
      "Engine Type",
      "Supply Only",
      "Fitted (Indie)",
      "Warranty",
      "Best For"
    ],
    "rows": [
      {
        "engineType": "Used Engine",
        "supplyOnly": "£400–£1,200",
        "fittedIndie": "£1,000–£2,200",
        "warranty": "1–6 months",
        "bestFor": "Budget priority; older M10/M40 examples"
      },
      {
        "engineType": "Reconditioned Engine",
        "supplyOnly": "£800–£2,200",
        "fittedIndie": "£1,800–£3,500",
        "warranty": "12–24 months",
        "bestFor": "Most owners — best cost/warranty balance"
      },
      {
        "engineType": "Rebuilt Engine",
        "supplyOnly": "£1,500–£3,500",
        "fittedIndie": "£2,800–£5,000",
        "warranty": "12–24 months",
        "bestFor": "Long-term ownership; 3+ year horizon"
      },
      {
        "engineType": "Main Dealer New",
        "supplyOnly": "N/A — no longer available",
        "fittedIndie": "N/A",
        "warranty": "—",
        "bestFor": "N/A — specialist rebuild only"
      }
    ],
    "figuresNote": "Figures above reflect the current market. Older M10 engines sit at the lower end; M43B19 engines command a premium. See the Era Map above for generation-specific context.",
    "labourEstimate": "Fitting a 518/518i engine typically takes 8–12 hours at £65–£95/hr (independent) or £110–£160/hr (London/SE dealer).",
    "cta": {
      "label": "→ Compare 518 / 518i engine prices from UK specialists",
      "href": "#"
    }
  },
  "commonProblems": {
    "problems": [
      {
        "id": 1,
        "title": "Timing Belt Failure (M10, M40)",
        "symptoms": "Engine stops suddenly, ticking from the front of the engine, complete loss of power, catastrophic engine failure",
        "typicalMileage": "40,000–60,000 miles (belt interval)",
        "repairCost": "£300–£600 (preventative timing belt replacement)",
        "replacementCost": "£500–£1,800 (if belt snaps — piston-valve contact)",
        "urgency": {
          "icon": "🔴",
          "label": "Immediate",
          "text": "if the belt fails, the engine stops instantly and internal damage is highly likely"
        },
        "recommendation": "The M10 and M40 engines use timing belts — not chains. BMW recommended replacement every 40,000–60,000 miles or 4–5 years. A snapped timing belt on these interference engines means valve and piston damage — effectively an engine replacement. If you're buying an older 518/518i with an M10 or M40 engine, demand proof of timing belt replacement. Budget for it immediately if there's no evidence. The M40 is particularly known for ticking lifters and belt wear.",
        "failureLink": {
          "label": "Read the full timing belt failure guide",
          "href": "/failures/timing-belt-failure/"
        }
      },
      {
        "id": 2,
        "title": "Cooling System and Head Gasket Issues (All Engines)",
        "symptoms": "Coolant loss, rising temperature gauge, white smoke from exhaust, \"mayo\" under the oil filler cap, overheating",
        "typicalMileage": "80,000–150,000 miles",
        "repairCost": "£500–£1,200 (head gasket replacement)",
        "replacementCost": "£800–£2,200 (if overheating causes bottom-end damage)",
        "urgency": {
          "icon": "🟠",
          "label": "Check",
          "text": "book inspection urgently"
        },
        "recommendation": "Like many older BMW engines, the M10, M40 and M43 can suffer from cooling system neglect. A failed water pump, clogged radiator, or old coolant can lead to overheating and head gasket failure. On the M43, cooling system leaks are a known issue — one owner reported losing half a litre of coolant every 5–8 days. Regular coolant changes and water pump replacement are essential. Catch overheating early and it's a manageable repair; ignore it and the head gasket fails.",
        "failureLink": {
          "label": "Read the full head gasket failure guide",
          "href": "/failures/head-gasket-failure/"
        }
      },
      {
        "id": 3,
        "title": "M40 Ticking Lifters and Camshaft Wear",
        "symptoms": "Loud ticking noise from the engine, especially when cold or at idle, loss of power, rough running",
        "typicalMileage": "60,000–120,000 miles",
        "repairCost": "£400–£1,000 (hydraulic lifter replacement or camshaft inspection)",
        "replacementCost": "N/A — repair only",
        "urgency": {
          "icon": "🟡",
          "label": "Monitor",
          "text": "book inspection soon"
        },
        "recommendation": "The M40 engine is notorious for ticking hydraulic lifters — they can sound like a sewing machine when revved. In some cases, the camshaft can wear excessively, limiting revs to 4,000–5,000 rpm. Regular oil changes with the correct grade can help. If the ticking becomes severe or the engine won't rev freely, have the lifters and camshaft inspected. Replacement is a well-understood job for any BMW specialist.",
        "failureLink": {
          "label": "Read the full lifter failure guide",
          "href": "/failures/hydraulic-lifter-failure/"
        }
      }
    ]
  },
  "quotesCta": {
    "headline": "Weighing Your Options? Compare Specialist Quotes When You're Ready →",
    "supportingLine": "20+ vetted BMW specialists, every 5 Series engine era covered, with a 12-month warranty as standard.",
    "button": {
      "label": "See BMW 518 / 518i Engine Options →",
      "href": "#"
    }
  },
  "repairBuyOrReplace": {
    "h2": "518 / 518i — Repair, Buy, or Replace?",
    "canItBeRepaired": {
      "title": "Can It Be Repaired?",
      "columns": [
        "Problem",
        "Repairable?",
        "Typical Cost",
        "When It Makes Sense"
      ],
      "rows": [
        {
          "problem": "Timing belt replacement (M10/M40)",
          "repairable": "✅ Yes",
          "typicalCost": "£300–£600",
          "whenItMakesSense": "Standard maintenance — the most important investment in these engines"
        },
        {
          "problem": "Timing belt failure (engine damage)",
          "repairable": "❌ Usually No",
          "typicalCost": "Engine replacement",
          "whenItMakesSense": "If belt snaps, valves hit pistons — replacement is the only option"
        },
        {
          "problem": "Head gasket failure",
          "repairable": "✅ Yes",
          "typicalCost": "£500–£1,200",
          "whenItMakesSense": "Well-understood job — cheaper than a full engine on a cherished example"
        },
        {
          "problem": "M40 ticking lifters",
          "repairable": "✅ Yes",
          "typicalCost": "£400–£1,000",
          "whenItMakesSense": "Replacement or inspection — well-understood by BMW specialists"
        },
        {
          "problem": "Cooling system neglect (overheating)",
          "repairable": "⚠️ Sometimes",
          "typicalCost": "£800–£2,200",
          "whenItMakesSense": "Viable on a low-mileage example; borderline on high-mileage"
        }
      ]
    },
    "buyingChecks": {
      "title": "Buying This 518 / 518i? Check These First",
      "buyIf": [
        "* M43-engined car (1994–2001) — the timing chain makes these significantly more reliable than belt-driven M10/M40 cars",
        "* M10 or M40 with documented timing belt replacement within the last 40,000–60,000 miles — the single most important check",
        "* Full service history with regular oil changes — these engines are robust but ageing",
        "* Evidence of cooling system maintenance — water pump and coolant changes"
      ],
      "avoidIf": [
        "* M10 or M40 with no proof of timing belt replacement — budget for it immediately or walk away",
        "* M40 with severe ticking that doesn't go away — could indicate camshaft wear",
        "* Any signs of overheating or coolant loss — head gasket or cooling system issues are likely",
        "* Poor service history — these engines are forgiving but not indestructible"
      ]
    },
    "closingVerdict": "The 518/518i badge spans 27 years and four engine families. The early M10 and M40 engines are simple, robust, but demand timing belt attention — a snapped belt is catastrophic. The M43 engines (1994–2001) are significantly more reliable thanks to the timing chain. If you're buying an M10 or M40 car, demand timing belt history. If you're buying an M43, you're getting BMW's most refined four-cylinder of the era. Buy on history, not on price.",
    "cta": {
      "label": "→ Compare 518 / 518i engine prices before you buy",
      "href": "#"
    }
  },
  "buyingChecklist": {
    "intro": "Before you buy a used BMW 518 or 518i (or before you commit to an engine replacement), check these:",
    "items": [
      "1. Timing Belt History (M10/M40) — Has it been changed within the last 40,000–60,000 miles or 4–5 years?",
      "2. Cold Start — Any ticking that doesn't go away? (M40 lifter or camshaft warning)",
      "3. Service History — including which engine era and evidence of timing belt/chain work",
      "4. Coolant Level — Any loss or signs of \"mayo\"? (head gasket or cooling system warning)",
      "5. Oil Condition — Any signs of coolant contamination? (milky appearance)",
      "6. Temperature Gauge — Any history of overheating?",
      "7. Engine Warning Light — Have codes been read? Any unresolved issues?",
      "8. MOT History — Check for emissions-related failures (catalyst, O2 sensors)"
    ]
  },
  "engineCodes": {
    "columns": [
      "Engine Code",
      "Years",
      "Power",
      "2025 Enquiries",
      "Avg. Recon Cost"
    ],
    "rows": [
      {
        "engineCode": "M10B18 (carb)",
        "years": "1974–1981",
        "power": "90 hp",
        "enquiries": "[PATTERN DATA]",
        "avgReconCost": "£500–£1,200 [BMW-QUOTE]"
      },
      {
        "engineCode": "M10B18 (injection)",
        "years": "1981–1987",
        "power": "102–105 hp",
        "enquiries": "[PATTERN DATA]",
        "avgReconCost": "£600–£1,400 [BMW-QUOTE]"
      },
      {
        "engineCode": "M40B18",
        "years": "1989–1994",
        "power": "113 hp",
        "enquiries": "[PATTERN DATA]",
        "avgReconCost": "£800–£1,800 [BMW-QUOTE]"
      },
      {
        "engineCode": "M43B18",
        "years": "1994–1995",
        "power": "115 hp",
        "enquiries": "[PATTERN DATA]",
        "avgReconCost": "£1,000–£2,200 [BMW-QUOTE]"
      },
      {
        "engineCode": "M43B19",
        "years": "1996–2001",
        "power": "118 hp",
        "enquiries": "[PATTERN DATA]",
        "avgReconCost": "£1,200–£2,800 [BMW-QUOTE]"
      }
    ],
    "matchNote": "This table's rows match Section 1B's Era Map exactly — five engine variants across the 518/518i's history.",
    "technicalSpecs": {
      "title": "Technical Specs (M43B19 — final generation):",
      "items": [
        {
          "label": "* Displacement",
          "value": "1,895cc (1.9-litre)"
        },
        {
          "label": "* Cylinders",
          "value": "4-cylinder inline"
        },
        {
          "label": "* Compression Ratio",
          "value": "9.7:1"
        },
        {
          "label": "* Fuel System",
          "value": "Bosch Motronic 1.7.3/2 fuel injection"
        },
        {
          "label": "* Valvetrain",
          "value": "SOHC, 8 valves, timing chain"
        }
      ]
    },
    "cta": {
      "label": "→ Compare 518 / 518i engine prices for your BMW",
      "href": "#"
    }
  },
  "marketIntelligence": {
    "items": []
  },
  "faq": {
    "items": [],
    "disclaimer": ""
  },
  "trustCta": {
    "h2": "",
    "trustPoints": [
      {
        "title": "Trusted 518 / 518i Engine Suppliers",
        "text": "every garage and engine rebuilder in our network is vetted, rated and reviewed by real 518 and 518i owners, as part of the Engine Finders network, across every generation from E12 to E39 — no matter which era your 5 Series belongs to."
      },
      {
        "title": "Compare 518 / 518i Engine Replacement Companies",
        "text": "see prices, warranty terms and supply & fit options side‑by‑side before you commit, with specialists who genuinely understand the timing belt, timing chain, and cooling system nuances of each 518/518i generation."
      },
      {
        "title": "UK Engine Replacement Services for 518 / 518i",
        "text": "supply‑only or full supply & fit available nationwide, covering every generation of this badge since 1974 with a 12‑month warranty as standard."
      }
    ],
    "finalCta": "Find the best BMW 518 or 518i engine replacement UK owners trust. Compare prices from trusted specialists on EnginesMarket today and keep your classic 5 Series on the road.",
    "ctaButton": {
      "label": "Explore BMW 518 / 518i Engine Quotes →",
      "href": "#"
    }
  }
}
